Workbook

Sheet Paper Review
A1: No. | B1: Title | C1: Authors | D1: Year | E1: Venue | F1: Link | G1: Theme | H1: Category | I1: Dataset(s) | J1: Detection Strategy | K1: Literature Review (positioning) | L1: Result (as reported by authors) | M1: Future Work | N1: Weakness | O1: How We Use It in the Proposal
A2: 1 | B2: CNN-Generated Images Are Surprisingly Easy to Spot... For Now | C2: S.-Y. Wang, O. Wang, R. Zhang, A. Owens, A. A. Efros | D2: 2020 | E2: CVPR 2020 | F2: https://arxiv.org/abs/1912.11035 | G2: Low-level artifact & frequency | H2: Artifact / CNN baseline | I2: ForenSynths: ProGAN (20 LSUN classes, 720k imgs) for training; 11 CNN generators for testing (StyleGAN, BigGAN, CycleGAN, StarGAN, GauGAN, CRN, IMLE, SITD, SAN, Deepfake, StyleGAN2) | J2: ResNet-50 binary classifier trained on a single GAN (ProGAN) with Gaussian-blur + JPEG augmentation to force reliance on generator-agnostic upsampling artifacts. | K2: Built on GAN-fingerprint work (Marra 2019, Yu 2019); first to show one-generator training can transfer across CNN generators. | L2: High average precision on most unseen GANs; blur/JPEG augmentation was key to robustness and cross-GAN transfer. | M2: Authors flag 'for now': predicts detection will get harder as generators improve; suggests studying newer architectures. | N2: Fails badly on diffusion and autoregressive models (later shown by Ojha 2023, Corvi 2023); relies on low-level traces easily destroyed by resizing. | O2: Standard baseline + ProGAN-4class training protocol (UniversalFakeDetect) used in our Protocol P1.
A3: 2 | B3: Leveraging Frequency Analysis for Deep Fake Image Recognition | C3: J. Frank, T. Eisenhofer, L. Schönherr, A. Fischer, D. Kolossa, T. Holz | D3: 2020 | E3: ICML 2020 | F3: https://arxiv.org/abs/2003.08685 | G3: Low-level artifact & frequency | H3: Frequency | I3: FFHQ/StyleGAN, LSUN bedrooms with ProGAN, SN-DCGAN, CramerGAN, MMDGAN | J3: 2D-DCT log spectrum as input to simple linear / CNN classifiers; shows upsampling produces grid artifacts in frequency space. | K3: Extends spectral analyses of GANs (Zhang 2019, Durall 2020) with a systematic DCT study. | L3: Near-perfect accuracy on GAN images with very simple classifiers in DCT domain; artifacts persist across architectures. | M3: Study defences against spectrum-matching generators. | N3: GAN-only; spectral cues are fragile to JPEG/resizing and diminished in diffusion outputs. | O3: Motivates frequency (DCT/FFT) features of Expert E1.
A4: 3 | B4: Watch your Up-Convolution: CNN Based Generative Deep Neural Networks are Failing to Reproduce Spectral Distributions | C4: R. Durall, M. Keuper, J. Keuper | D4: 2020 | E4: CVPR 2020 | F4: https://arxiv.org/abs/2003.01826 | G4: Low-level artifact & frequency | H4: Frequency | I4: FaceForensics++, CelebA, Faces-HQ (StyleGAN/PGGAN faces) | J4: Azimuthally-averaged 1D power spectrum as feature; spectral regularisation term proposed for generators. | K4: Theoretical link between transposed convolution and high-frequency spectral distortions. | L4: Very high detection accuracy with simple 1D spectral features on face GAN data. | M4: Spectral-regularised generators; detection of next-gen generators. | N4: Easily evaded by spectral-loss training; GAN-face focused. | O4: Azimuthal power spectrum P(r) used as hand-crafted feature in E1.
A5: 4 | B5: Detecting and Simulating Artifacts in GAN Fake Images (AutoGAN) | C5: X. Zhang, S. Karaman, S.-F. Chang | D5: 2019 | E5: IEEE WIFS 2019 | F5: https://arxiv.org/abs/1907.06515 | G5: Low-level artifact & frequency | H5: Frequency / simulation | I5: CycleGAN image-to-image translations (multiple categories) | J5: AutoGAN simulator reproduces up-sampling artifacts without access to the target GAN; spectrum-based classifier. | K5: Early analysis of checkerboard artifacts from upsampling. | L5: Spectrum-input classifier generalised well across unseen CycleGAN categories. | M5: Use simulators to generate training data cheaply. | N5: Image-to-image GANs only; simulator does not cover diffusion pipelines. | O5: Idea of artefact simulation echoed by our VAE-reconstruction alignment (no new data collection needed).
A6: 5 | B6: Do GANs Leave Artificial Fingerprints? | C6: F. Marra, D. Gragnaniello, L. Verdoliva, G. Poggi | D6: 2019 | E6: IEEE MIPR 2019 | F6: https://arxiv.org/abs/1812.11842 | G6: Low-level artifact & frequency | H6: Fingerprint / attribution | I6: CycleGAN, ProGAN images and real camera images | J6: Noise residuals (denoiser-based) averaged to obtain GAN-specific fingerprints, analogous to PRNU in cameras. | K6: Transfers camera forensics (PRNU) to generators. | L6: Shows each GAN leaves a stable fingerprint that allows source attribution. | M6: Fingerprints for more architectures; robustness studies. | N6: Requires many samples per generator; fingerprints weaken under compression. | O6: Noise-residual idea used in E1 (SRM/denoiser residual stream).
A7: 6 | B7: What Makes Fake Images Detectable? Understanding Properties that Generalize | C7: L. Chai, D. Bau, S.-N. Lim, P. Isola | D7: 2020 | E7: ECCV 2020 | F7: https://arxiv.org/abs/2008.10588 | G7: Low-level artifact & frequency | H7: Patch-level artifact | I7: CelebA-HQ / FFHQ faces from PGAN, SGAN, Glow, GMM | J7: Truncated ResNet/Xception with limited receptive field classifies local patches; heatmaps show where artifacts are. | K7: Questions global classifiers; argues local texture generalises better. | L7: Patch classifiers generalise better than full-image classifiers; hair and background regions most informative. | M7: Adversarially generated fakes that remove local artifacts. | N7: Face-only; generator fine-tuned against the detector evades it. | O7: Patch-level native-resolution cropping and patch voting in E1.
A8: 7 | B8: Are GAN Generated Images Easy to Detect? A Critical Analysis of the State-of-the-Art | C8: D. Gragnaniello, D. Cozzolino, F. Marra, G. Poggi, L. Verdoliva | D8: 2021 | E8: ICME 2021 | F8: https://arxiv.org/abs/2104.02617 | G8: Low-level artifact & frequency | H8: Artifact / analysis | I8: ForenSynths + StyleGAN2 and others | J8: Modified ResNet-50 without early down-sampling to preserve high-frequency traces; studies training choices. | K8: Critical re-examination of CNNSpot. | L8: Avoiding down-sampling in the first layer significantly improves generalisation and robustness. | M8: Evaluate on newer generators. | N8: Still GAN focused; compute heavier due to no down-sampling. | O8: Supports keeping full-resolution early layers in E1.
A9: 8 | B9: Detecting Generated Images by Real Images (LNP) | C9: B. Liu, F. Yang, X. Bi, B. Xiao, W. Li, X. Gao | D9: 2022 | E9: ECCV 2022 | F9: https://scholar.google.com/scholar?q=Detecting+Generated+Images+by+Real+Images+ECCV+2022 | G9: Low-level artifact & frequency | H9: Noise residual | I9: Multiple GAN and some DM sets; trained largely on real images | J9: Learned Noise Patterns (LNP) from a denoising network; real images share consistent noise patterns, generated ones deviate (one-class flavour). | K9: Camera-noise forensics applied to synthesis. | L9: Good generalisation including to unseen generators with mostly real data training. | M9: Robustness to compression. | N9: Noise traces destroyed by heavy JPEG/resizing. | O9: Supports 'model the real distribution' idea (Stay-Positive, one-class regulariser).
A10: 9 | B10: Learning on Gradients: Generalized Artifacts Representation for GAN-Generated Images Detection (LGrad) | C10: C. Tan, Y. Zhao, S. Wei, G. Gu, Y. Wei | D10: 2023 | E10: CVPR 2023 | F10: https://scholar.google.com/scholar?q=Learning+on+Gradients+Generalized+Artifacts+Representation+GAN-Generated+Images+Detection | G10: Low-level artifact & frequency | H10: Artifact representation | I10: ForenSynths ProGAN train; multiple GANs test | J10: Uses gradients of a pretrained CNN w.r.t. the input as a generalised artifact representation, then classifies gradient maps. | K10: Moves from raw pixels to model-gradient features. | L10: Clear accuracy gains over CNNSpot on unseen GANs. | M10: Diffusion generalisation. | N10: Depends on choice of pretrained transformation model; weaker on diffusion. | O10: Candidate alternative low-level representation in E1 ablation.
A11: 10 | B11: Rethinking the Up-Sampling Operations in CNN-based Generative Network for Generalizable Deepfake Detection (NPR) | C11: C. Tan, H. Liu, Y. Zhao, S. Wei, G. Gu, P. Liu, Y. Wei | D11: 2024 | E11: CVPR 2024 | F11: https://arxiv.org/abs/2312.10461 | G11: Low-level artifact & frequency | H11: Artifact representation | I11: ProGAN-4class train; tested on ~28 GAN/DM generators (ForenSynths, UFD, GenImage, DiffusionForensics) | J11: Neighbouring Pixel Relationships: residual between image and its nearest-neighbour down/up-sampled version exposes local up-sampling correlations. | K11: Generalises frequency artifact work to a simple spatial operator. | L11: Reported ~12-point average accuracy gain over prior SOTA across many unseen generators with a light ResNet. | M11: Theory of up-sampling across architectures. | N11: Sensitive to JPEG and resizing; recent work shows drops in the wild (AIGIBench, Chameleon). | O11: NPR residual is one input stream of E1.
A12: 11 | B12: Frequency-Aware Deepfake Detection: Improving Generalizability through Frequency Space Learning (FreqNet) | C12: C. Tan, Y. Zhao, S. Wei, G. Gu, P. Liu, Y. Wei | D12: 2024 | E12: AAAI 2024 | F12: https://arxiv.org/abs/2403.07240 | G12: Low-level artifact & frequency | H12: Frequency | I12: ProGAN-4class train; 17 GANs/DMs test | J12: Frequency-space learning: high-frequency representation + convolution in phase/amplitude spectra inside a lightweight CNN. | K12: Prior frequency detectors used fixed spectra; FreqNet learns in frequency space. | L12: Better generalisation than NPR's predecessors with ~1.9M parameters. | M12: Combine with semantic cues. | N12: Frequency cues fragile under laundering. | O12: Inspires learnable spectral convolution in E1.
A13: 12 | B13: PatchCraft: Exploring Texture Patch for Efficient AI-generated Image Detection | C13: N. Zhong, Y. Xu, S. Li, Z. Qian, X. Zhang | D13: 2023 | E13: arXiv 2023 | F13: https://arxiv.org/abs/2311.12397 | G13: Low-level artifact & frequency | H13: Texture contrast | I13: Large self-built benchmark of 16 generators (GAN + DM + commercial) | J13: Smash & Reconstruction: rich- vs poor-texture patches; inter-pixel correlation contrast between them via high-pass filters. | K13: Argues semantic content biases detectors. | L13: Strong cross-generator accuracy on its benchmark. | M13: Robustness to compression. | N13: Patch selection heuristic; degraded by JPEG/resize. | O13: Rich/poor texture patch sampling used in our crop strategy.
... A101: 100 | B101: The Stable Signature: Rooting Watermarks in Latent Diffusion Models | C101: P. Fernandez, G. Couairon, H. Jégou, M. Douze, T. Furon | D101: 2023 | E101: ICCV 2023 | F101: https://arxiv.org/abs/2303.15435 | G101: Proactive provenance (watermark) | H101: Watermark (proactive) | I101: SD-generated images | J101: Fine-tunes LDM decoder so all outputs carry a binary signature. | K101: In-model watermarking. | L101: Detects >90% of generated images even after cropping at very low FPR. | M101: — | N101: Open-source models can be modified to remove it. | O101: Complementary; motivates passive detection.

Sheet Summary
A1: Theme | B1: Number of papers | C1: Share
A2: 3D geometry & physics | B2: =COUNTIF('Paper Review'!$G$2:$G$101,A2) -> 5 | C2: =B2/$B$11 -> 0.05
A3: Adversarial robustness | B3: =COUNTIF('Paper Review'!$G$2:$G$101,A3) -> 9 | C3: =B3/$B$11 -> 0.09
A4: Data-centric / bias-free training | B4: =COUNTIF('Paper Review'!$G$2:$G$101,A4) -> 6 | C4: =B4/$B$11 -> 0.06
A5: Datasets & benchmarks | B5: =COUNTIF('Paper Review'!$G$2:$G$101,A5) -> 14 | C5: =B5/$B$11 -> 0.14
A6: Foundation-model / VLM features | B6: =COUNTIF('Paper Review'!$G$2:$G$101,A6) -> 19 | C6: =B6/$B$11 -> 0.19
A7: Low-level artifact & frequency | B7: =COUNTIF('Paper Review'!$G$2:$G$101,A7) -> 19 | C7: =B7/$B$11 -> 0.19
A8: MLLM / LLM reasoning & explanation | B8: =COUNTIF('Paper Review'!$G$2:$G$101,A8) -> 14 | C8: =B8/$B$11 -> 0.14
A9: Proactive provenance (watermark) | B9: =COUNTIF('Paper Review'!$G$2:$G$101,A9) -> 2 | C9: =B9/$B$11 -> 0.02
A10: Reconstruction / zero-shot | B10: =COUNTIF('Paper Review'!$G$2:$G$101,A10) -> 12 | C10: =B10/$B$11 -> 0.12
A11: Total | B11: =SUM(B2:B10) -> 100 | C11: =SUM(C2:C10) -> 1
A13: Year | B13: Number of papers
A14: 2018 | B14: =COUNTIF('Paper Review'!$D$2:$D$101,2018) -> 1
A15: 2019 | B15: =COUNTIF('Paper Review'!$D$2:$D$101,2019) -> 3
A16: 2020 | B16: =COUNTIF('Paper Review'!$D$2:$D$101,2020) -> 5
A17: 2021 | B17: =COUNTIF('Paper Review'!$D$2:$D$101,2021) -> 1
A18: 2022 | B18: =COUNTIF('Paper Review'!$D$2:$D$101,2022) -> 3
A19: 2023 | B19: =COUNTIF('Paper Review'!$D$2:$D$101,2023) -> 17
A20: 2024 | B20: =COUNTIF('Paper Review'!$D$2:$D$101,2024) -> 28
A21: 2025 | B21: =COUNTIF('Paper Review'!$D$2:$D$101,2025) -> 31
A22: 2026 | B22: =COUNTIF('Paper Review'!$D$2:$D$101,2026) -> 11

Sheet Notes
A1: How to read this sheet
A2: • Results are as reported by the paper's authors (abstract / main tables). Numbers are approximate where marked '~'; consult the paper for exact tables before citing numbers in the manuscript.
A3: • Links go to arXiv when an arXiv ID was confirmed; otherwise to the official venue page or a Google Scholar search for the exact title.
A4: • For very recent preprints (2025–2026) only the abstract-level information was available; their 'Future Work' / 'Weakness' cells are flagged accordingly ('Preprint', '—').
A5: • 'How We Use It' maps each paper to a component of the proposed PRISM framework: E1 = low-level artifact & spectral expert, E2 = foundation-model semantic expert, E3 = generative-reconstruction expert, E4 = 3D geometry & physics expert, MLLM = evidence-conditioned reasoning layer, P1–P7 = evaluation protocols.
A6: • Use the filter on the 'Theme' column of 'Paper Review' to read papers by theme; the 'Summary' tab counts papers per theme and year with live formulas.
A7: Compiled 11 Oct 2026.
